{"instargram":null,"company":null,"createDate":"2024-10-31 12:26:26","sooniCompany":"수니게임즈","activaFlag":null,"position":null,"blood":"B","soopName":"헤니","namu":null,"birthday":"1997-02-15","personName":null,"weight":null,"grade":null,"sex":"W","sooniName":"헤니","youtube":null,"team":null,"nickHistory":null,"updateDate":"2025-07-22 21:53:52","activeFlag":"Y","soopId":"jhw215","tall":null,"status":"Y","sooniEngName":null,"medal":"best","broadCast":"2023-07-22","mbti":["ISFP"],"remark":"수니게임즈 멤버","manager":null,"stages":[],"ballons":[]}