{"namu":null,"personName":"","activeFlag":"Y","sex":"W","nickHistory":null,"broadCast":null,"company":"","sooniEngName":"","soopId":"youjamjam","medal":"best","grade":"","createDate":"2025-05-05 23:03:20","instargram":"youjam_jam","updateDate":"2025-07-31 21:23:42","youtube":"@youjamjam","weight":null,"remark":null,"position":"","status":"Y","birthday":"1997-06-10","sooniName":"유잼이","mbti":["ISTP"],"tall":"162","team":"","manager":"","sooniCompany":"수니게임즈","blood":"A","soopName":"유잼이","stages":[],"ballons":[]}