{
  "SigList": [
    {
        "sigName": "구미베어",
        "sigValue": 1000,
        "imgId": 2416001,
        "isNew": false,
        "id": "143677113",
        "sigCount": 233
    },
    {
        "sigName": "NA",
        "sigValue": 1050,
        "imgId": 2416002,
        "isNew": false,
        "id": "143677887",
        "sigCount": 4
    },
    {
        "sigName": "옴브리뉴",
        "sigValue": 1080,
        "imgId": 2416003,
        "isNew": false,
        "id": "143678889",
        "sigCount": 35
    },
    {
        "sigName": "홀덥",
        "sigValue": 1100,
        "imgId": 2416004,
        "isNew": false,
        "id": "143678251",
        "sigCount": 15
    },
    {
        "sigName": "Emergency",
        "sigValue": 1111,
        "imgId": 2416005,
        "isNew": false,
        "id": "143683333",
        "sigCount": 10
    },
    {
        "sigName": "삐끼삐끼",
        "sigValue": 1150,
        "imgId": 2416006,
        "isNew": false,
        "id": "143678463",
        "sigCount": 3
    },
    {
        "sigName": "블루먼데이",
        "sigValue": 1200,
        "imgId": 2416007,
        "isNew": false,
        "id": "143688589",
        "sigCount": 1
    },
    {
        "sigName": "마그네틱",
        "sigValue": 1220,
        "imgId": 2416008,
        "isNew": false,
        "id": "143682811",
        "sigCount": 3
    },
    {
        "sigName": "슈퍼소닉",
        "sigValue": 1232,
        "imgId": 2416009,
        "isNew": false,
        "id": "143681155",
        "sigCount": 2
    },
    {
        "sigName": "영차",
        "sigValue": 1252,
        "imgId": 2416010,
        "isNew": false,
        "id": "143687229",
        "sigCount": 2
    },
    {
        "sigName": "수수께끼다이어리",
        "sigValue": 1280,
        "imgId": 2416011,
        "isNew": false,
        "id": "X",
        "sigCount": -1
    },
    {
        "sigName": "Pose",
        "sigValue": 1300,
        "imgId": 2416012,
        "isNew": false,
        "id": "143679649",
        "sigCount": 35
    },
    {
        "sigName": "미스터빈",
        "sigValue": 1313,
        "imgId": 2416013,
        "isNew": false,
        "id": "143687899",
        "sigCount": 2
    },
    {
        "sigName": "아무거나잘춰",
        "sigValue": 1328,
        "imgId": 2416014,
        "isNew": true,
        "id": "X",
        "sigCount": -1
    },
    {
        "sigName": "기리기리",
        "sigValue": 1330,
        "imgId": 2416015,
        "isNew": false,
        "id": "X",
        "sigCount": -1
    },
    {
        "sigName": "킥드럼베이스",
        "sigValue": 1350,
        "imgId": 2416016,
        "isNew": false,
        "id": "143682245",
        "sigCount": 20
    },
    {
        "sigName": "아이스크림",
        "sigValue": 1380,
        "imgId": 2416017,
        "isNew": false,
        "id": "143676457",
        "sigCount": 7
    },
    {
        "sigName": "큰거온다",
        "sigValue": 1400,
        "imgId": 2416018,
        "isNew": false,
        "id": "143686237",
        "sigCount": 6
    },
    {
        "sigName": "포케댄스",
        "sigValue": 1425,
        "imgId": 2416019,
        "isNew": false,
        "id": "143684489",
        "sigCount": 5
    },
    {
        "sigName": "교통정리",
        "sigValue": 1432,
        "imgId": 2416020,
        "isNew": false,
        "id": "143683503",
        "sigCount": 5
    },
    {
        "sigName": "냠냠냠",
        "sigValue": 1446,
        "imgId": 2416021,
        "isNew": true,
        "id": "X",
        "sigCount": -1
    },
    {
        "sigName": "러쉬아워",
        "sigValue": 1452,
        "imgId": 2416022,
        "isNew": false,
        "id": "143683103",
        "sigCount": 2
    },
    {
        "sigName": "스티키",
        "sigValue": 1480,
        "imgId": 2416023,
        "isNew": false,
        "id": "X",
        "sigCount": -1
    },
    {
        "sigName": "역도",
        "sigValue": 1500,
        "imgId": 2416024,
        "isNew": false,
        "id": "143677563",
        "sigCount": 29
    },
    {
        "sigName": "꽃",
        "sigValue": 1533,
        "imgId": 2416025,
        "isNew": false,
        "id": "143682027",
        "sigCount": 5
    },
    {
        "sigName": "DRIP",
        "sigValue": 1545,
        "imgId": 2416026,
        "isNew": true,
        "id": "143680221",
        "sigCount": 3
    },
    {
        "sigName": "퐁당퐁당",
        "sigValue": 1550,
        "imgId": 2416027,
        "isNew": false,
        "id": "X",
        "sigCount": -1
    },
    {
        "sigName": "키티켓",
        "sigValue": 1572,
        "imgId": 2416028,
        "isNew": false,
        "id": "143679505",
        "sigCount": 2
    },
    {
        "sigName": "룩앳미",
        "sigValue": 1585,
        "imgId": 2416029,
        "isNew": false,
        "id": "X",
        "sigCount": -1
    },
    {
        "sigName": "망치들라",
        "sigValue": 1600,
        "imgId": 2416030,
        "isNew": false,
        "id": "143686629",
        "sigCount": 2
    },
    {
        "sigName": "ERG",
        "sigValue": 1616,
        "imgId": 2416031,
        "isNew": false,
        "id": "143685593",
        "sigCount": 2
    },
    {
        "sigName": "LIKE THAT",
        "sigValue": 1623,
        "imgId": 2416032,
        "isNew": true,
        "id": "143676249",
        "sigCount": 1
    },
    {
        "sigName": "러브럼펌펌",
        "sigValue": 1644,
        "imgId": 2416033,
        "isNew": false,
        "id": "143678737",
        "sigCount": 2
    },
    {
        "sigName": "슈퍼내추럴",
        "sigValue": 1650,
        "imgId": 2416034,
        "isNew": false,
        "id": "143688513",
        "sigCount": 2
    },
    {
        "sigName": "파이팅해야지",
        "sigValue": 1660,
        "imgId": 2416035,
        "isNew": false,
        "id": "143683565",
        "sigCount": 2
    },
    {
        "sigName": "야레야레",
        "sigValue": 1680,
        "imgId": 2416036,
        "isNew": false,
        "id": "143687485",
        "sigCount": 1
    },
    {
        "sigName": "베이프",
        "sigValue": 1688,
        "imgId": 2416037,
        "isNew": false,
        "id": "X",
        "sigCount": -1
    },
    {
        "sigName": "BASE",
        "sigValue": 1700,
        "imgId": 2416038,
        "isNew": false,
        "id": "143681445",
        "sigCount": 2
    },
    {
        "sigName": "첫.계.않",
        "sigValue": 1730,
        "imgId": 2416039,
        "isNew": false,
        "id": "X",
        "sigCount": -1
    },
    {
        "sigName": "필더리듬",
        "sigValue": 1742,
        "imgId": 2416040,
        "isNew": false,
        "id": "X",
        "sigCount": -1
    },
    {
        "sigName": "댄스위드미",
        "sigValue": 1762,
        "imgId": 2416041,
        "isNew": true,
        "id": "X",
        "sigCount": -1
    },
    {
        "sigName": "나루토",
        "sigValue": 1777,
        "imgId": 2416042,
        "isNew": false,
        "id": "143678999",
        "sigCount": 4
    },
    {
        "sigName": "핑퐁",
        "sigValue": 1780,
        "imgId": 2416043,
        "isNew": false,
        "id": "X",
        "sigCount": -1
    },
    {
        "sigName": "오빠달려붕붕",
        "sigValue": 1800,
        "imgId": 2416044,
        "isNew": false,
        "id": "143687963",
        "sigCount": 1
    },
    {
        "sigName": "스모크",
        "sigValue": 1818,
        "imgId": 2416045,
        "isNew": false,
        "id": "143686079",
        "sigCount": 1
    },
    {
        "sigName": "러브쉐이크",
        "sigValue": 1829,
        "imgId": 2416046,
        "isNew": false,
        "id": "X",
        "sigCount": -1
    },
    {
        "sigName": "Dark Sight",
        "sigValue": 1844,
        "imgId": 2416047,
        "isNew": true,
        "id": "X",
        "sigCount": -1
    },
    {
        "sigName": "Atmosphere",
        "sigValue": 1850,
        "imgId": 2416048,
        "isNew": false,
        "id": "143686025",
        "sigCount": 2
    },
    {
        "sigName": "앙카",
        "sigValue": 1858,
        "imgId": 2416049,
        "isNew": false,
        "id": "X",
        "sigCount": -1
    },
    {
        "sigName": "EDEDM",
        "sigValue": 1880,
        "imgId": 2416050,
        "isNew": false,
        "id": "X",
        "sigCount": -1
    },
    {
        "sigName": "밤양갱갱갱",
        "sigValue": 1900,
        "imgId": 2416051,
        "isNew": false,
        "id": "143692169",
        "sigCount": 1
    },
    {
        "sigName": "러브나인",
        "sigValue": 1909,
        "imgId": 2416052,
        "isNew": false,
        "id": "X",
        "sigCount": -1
    },
    {
        "sigName": "우유",
        "sigValue": 1919,
        "imgId": 2416053,
        "isNew": false,
        "id": "X",
        "sigCount": -1
    },
    {
        "sigName": "색스폰매직",
        "sigValue": 1930,
        "imgId": 2416054,
        "isNew": false,
        "id": "143678363",
        "sigCount": 1
    },
    {
        "sigName": "DOODLE",
        "sigValue": 1950,
        "imgId": 2416055,
        "isNew": false,
        "id": "X",
        "sigCount": -1
    },
    {
        "sigName": "아마겟돈",
        "sigValue": 1960,
        "imgId": 2416056,
        "isNew": false,
        "id": "X",
        "sigCount": -1
    },
    {
        "sigName": "붐붐베이스",
        "sigValue": 1980,
        "imgId": 2416057,
        "isNew": false,
        "id": "X",
        "sigCount": -1
    },
    {
        "sigName": "헨타이",
        "sigValue": 1988,
        "imgId": 2416058,
        "isNew": false,
        "id": "143681273",
        "sigCount": 3
    },
    {
        "sigName": "간바레",
        "sigValue": 2000,
        "imgId": 2416059,
        "isNew": false,
        "id": "143677185",
        "sigCount": 56
    },
    {
        "sigName": "빛을따라서",
        "sigValue": 2020,
        "imgId": 2416060,
        "isNew": false,
        "id": "X",
        "sigCount": -1
    },
    {
        "sigName": "네모네모",
        "sigValue": 2035,
        "imgId": 2416061,
        "isNew": false,
        "id": "143684411",
        "sigCount": 1
    },
    {
        "sigName": "Whiplash",
        "sigValue": 2044,
        "imgId": 2416062,
        "isNew": false,
        "id": "143679855",
        "sigCount": 13
    },
    {
        "sigName": "GGUM",
        "sigValue": 2050,
        "imgId": 2416063,
        "isNew": false,
        "id": "X",
        "sigCount": -1
    },
    {
        "sigName": "MEOW",
        "sigValue": 2060,
        "imgId": 2416064,
        "isNew": false,
        "id": "143679123",
        "sigCount": 1
    },
    {
        "sigName": "이쿠욧",
        "sigValue": 2098,
        "imgId": 2416065,
        "isNew": false,
        "id": "X",
        "sigCount": -1
    },
    {
        "sigName": "Touch",
        "sigValue": 2112,
        "imgId": 2416066,
        "isNew": false,
        "id": "X",
        "sigCount": -1
    },
    {
        "sigName": "레디올낫",
        "sigValue": 2121,
        "imgId": 2416067,
        "isNew": false,
        "id": "143682167",
        "sigCount": 6
    },
    {
        "sigName": "클락션",
        "sigValue": 2143,
        "imgId": 2416068,
        "isNew": false,
        "id": "X",
        "sigCount": -1
    },
    {
        "sigName": "데킬라",
        "sigValue": 2150,
        "imgId": 2416069,
        "isNew": false,
        "id": "X",
        "sigCount": -1
    },
    {
        "sigName": "비키니파티",
        "sigValue": 2219,
        "imgId": 2416070,
        "isNew": false,
        "id": "X",
        "sigCount": -1
    },
    {
        "sigName": "아파트",
        "sigValue": 2222,
        "imgId": 2416071,
        "isNew": false,
        "id": "143682499",
        "sigCount": 7
    },
    {
        "sigName": "클라쓰",
        "sigValue": 2332,
        "imgId": 2416072,
        "isNew": false,
        "id": "X",
        "sigCount": -1
    },
    {
        "sigName": "삐삐",
        "sigValue": 2377,
        "imgId": 2416073,
        "isNew": false,
        "id": "X",
        "sigCount": -1
    },
    {
        "sigName": "대환장파티",
        "sigValue": 2482,
        "imgId": 2416074,
        "isNew": false,
        "id": "143687687",
        "sigCount": 1
    },
    {
        "sigName": "푱푱",
        "sigValue": 2488,
        "imgId": 2416075,
        "isNew": false,
        "id": "143688077",
        "sigCount": 1
    },
    {
        "sigName": "W.T.F",
        "sigValue": 2500,
        "imgId": 2416076,
        "isNew": false,
        "id": "X",
        "sigCount": -1
    },
    {
        "sigName": "코카인",
        "sigValue": 2519,
        "imgId": 2416077,
        "isNew": false,
        "id": "X",
        "sigCount": -1
    },
    {
        "sigName": "빠라뉴",
        "sigValue": 2558,
        "imgId": 2416078,
        "isNew": false,
        "id": "143685435",
        "sigCount": 1
    },
    {
        "sigName": "L.S.D",
        "sigValue": 2590,
        "imgId": 2416079,
        "isNew": false,
        "id": "X",
        "sigCount": -1
    },
    {
        "sigName": "핑크레이디",
        "sigValue": 2600,
        "imgId": 2416080,
        "isNew": false,
        "id": "143687611",
        "sigCount": 1
    },
    {
        "sigName": "왜요왜요",
        "sigValue": 2626,
        "imgId": 2416081,
        "isNew": false,
        "id": "143681025",
        "sigCount": 3
    },
    {
        "sigName": "파티트레인",
        "sigValue": 2660,
        "imgId": 2416082,
        "isNew": false,
        "id": "X",
        "sigCount": -1
    },
    {
        "sigName": "오렌지디스코",
        "sigValue": 2700,
        "imgId": 2416083,
        "isNew": false,
        "id": "X",
        "sigCount": -1
    },
    {
        "sigName": "Rich",
        "sigValue": 2727,
        "imgId": 2416084,
        "isNew": true,
        "id": "X",
        "sigCount": -1
    },
    {
        "sigName": "우치다",
        "sigValue": 2750,
        "imgId": 2416085,
        "isNew": false,
        "id": "X",
        "sigCount": -1
    },
    {
        "sigName": "판타스틱베이비",
        "sigValue": 2784,
        "imgId": 2416086,
        "isNew": false,
        "id": "X",
        "sigCount": -1
    },
    {
        "sigName": "Whereweare",
        "sigValue": 2800,
        "imgId": 2416087,
        "isNew": false,
        "id": "X",
        "sigCount": -1
    },
    {
        "sigName": "버터플라이",
        "sigValue": 2855,
        "imgId": 2416088,
        "isNew": false,
        "id": "X",
        "sigCount": -1
    },
    {
        "sigName": "패스트카",
        "sigValue": 2880,
        "imgId": 2416089,
        "isNew": false,
        "id": "X",
        "sigCount": -1
    },
    {
        "sigName": "바우치",
        "sigValue": 2900,
        "imgId": 2416090,
        "isNew": false,
        "id": "143692043",
        "sigCount": 2
    },
    {
        "sigName": "너와의 모든 지금",
        "sigValue": 2929,
        "imgId": 2416091,
        "isNew": true,
        "id": "143679267",
        "sigCount": 3
    },
    {
        "sigName": "외모췍",
        "sigValue": 2979,
        "imgId": 2416092,
        "isNew": false,
        "id": "X",
        "sigCount": -1
    },
    {
        "sigName": "아헤가오",
        "sigValue": 3000,
        "imgId": 2416093,
        "isNew": false,
        "id": "143677305",
        "sigCount": 65
    },
    {
        "sigName": "Be Alright",
        "sigValue": 3131,
        "imgId": 2416094,
        "isNew": true,
        "id": "X",
        "sigCount": -1
    },
    {
        "sigName": "Sayyes",
        "sigValue": 3333,
        "imgId": 2416095,
        "isNew": false,
        "id": "143683459",
        "sigCount": 3
    },
    {
        "sigName": "터미널",
        "sigValue": 3500,
        "imgId": 2416096,
        "isNew": false,
        "id": "143680933",
        "sigCount": 6
    },
    {
        "sigName": "파티락킹",
        "sigValue": 4000,
        "imgId": 2416097,
        "isNew": false,
        "id": "143682625",
        "sigCount": 6
    },
    {
        "sigName": "나르코",
        "sigValue": 5000,
        "imgId": 2416098,
        "isNew": false,
        "id": "143676925",
        "sigCount": 87
    },
    {
        "sigName": "코코로",
        "sigValue": 6000,
        "imgId": 2416099,
        "isNew": false,
        "id": "143684025",
        "sigCount": 5
    },
    {
        "sigName": "샤캬붐",
        "sigValue": 7000,
        "imgId": 2416100,
        "isNew": false,
        "id": "143678137",
        "sigCount": 2
    },
    {
        "sigName": "DERP",
        "sigValue": 8000,
        "imgId": 2416101,
        "isNew": false,
        "id": "143688343",
        "sigCount": 1
    },
    {
        "sigName": "Control",
        "sigValue": 9000,
        "imgId": 2416102,
        "isNew": false,
        "id": "X",
        "sigCount": -1
    },
    {
        "sigName": "보라빛밤",
        "sigValue": 10000,
        "imgId": 2416103,
        "isNew": false,
        "id": "143678621",
        "sigCount": 56
    },
    {
        "sigName": "남순로겐",
        "sigValue": 12486,
        "imgId": 2416104,
        "isNew": false,
        "id": "143681607",
        "sigCount": 7
    },
    {
        "sigName": "Get it",
        "sigValue": 20000,
        "imgId": 2416105,
        "isNew": false,
        "id": "143680053",
        "sigCount": 10
    },
    {
        "sigName": "Steps",
        "sigValue": 23456,
        "imgId": 2416106,
        "isNew": false,
        "id": "X",
        "sigCount": -1
    },
    {
        "sigName": "런투더스카이",
        "sigValue": 30000,
        "imgId": 2416107,
        "isNew": false,
        "id": "143684155",
        "sigCount": 9
    },
    {
        "sigName": "VIP",
        "sigValue": 100000,
        "imgId": 2416108,
        "isNew": false,
        "id": "143682983",
        "sigCount": 1
    }
  ]
}