[{"position":null,"personName":"박현우","blood":"B","activeFlag":"Y","sooniEngName":"NamSoon","sex":"M","createDate":"2024-10-31 12:26:26","grade":"회장","updateDate":"2025-09-29 10:40:17","company":"","nickHistory":null,"team":null,"soopId":"wnnw","mbti":["INTP"],"manager":"회장","medal":"partner","instargram":"wnnw2","status":"Y","tall":"175","remark":null,"weight":"68","sooniCompany":"수니그룹","youtube":"@Namsoon","activaFlag":null,"birthday":"1989-04-20","namu":"남순","sooniName":"남순","broadCast":"2012-01-10","soopName":"남순"},{"company":"FA","sex":"W","status":"Y","mbti":["ISFP"],"soopId":"fall0715","instargram":"fall0715","sooniEngName":"","medal":"partner","youtube":"@가을fall0715","updateDate":"2025-10-10 09:13:28","broadCast":"2016-01-30","birthday":"1994-07-15","soopName":"가을님","blood":"AB","nickHistory":null,"position":null,"personName":"박가을","tall":"168","activeFlag":"Y","weight":"53","sooniName":"가을","manager":"실장","createDate":"2025-07-06 18:55:25","team":null,"remark":null,"grade":"실장","namu":"가을(인터넷 방송인)","sooniCompany":"수니그룹"},{"nickHistory":null,"weight":null,"soopId":"leesb98","medal":"best","blood":"A","sooniEngName":"LeeSeungBin","personName":"이승빈","sooniName":"이승빈","position":null,"mbti":"ENFJ","sex":"M","activeFlag":"Y","tall":"172","updateDate":"2025-10-22 21:06:36","team":null,"sooniCompany":"수니그룹","grade2":null,"grade":"PD","ballon":null,"status":"Y","broadCast":"2022-12-08","createDate":"2024-10-31 12:26:26","remark":null,"birthday":"2001-09-08","youtube":"@이승빈","company":"FA","manager":"PD","soopName":"이승빈","namu":"이승빈(음악가)","instargram":"lsb_seungbinlee"},{"instargram":"ryuha_zzang","sex":"W","mbti":"INFJ","position":"","status":"Y","birthday":"1997-07-25","weight":"51","medal":"best","activeFlag":"Y","remark":null,"broadCast":"2021-01-07","tall":"166","createDate":"2024-10-31 12:26:26","nickHistory":null,"company":"수니뮤직","team":"엔소울","namu":"류하","sooniName":"류하","blood":"A","grade":"골드","youtube":"@RYUHAZZANG","soopName":"류하","soopId":"rrrr4719","sooniEngName":"RyuHa","grade2":"골드1","manager":"사장","updateDate":"2025-10-30 06:48:32","ballon":"515368","sooniCompany":"수니그룹","personName":"유인선"},{"youtube":"Baegna","personName":"박은화","grade":"골드","weight":"49","instargram":"baegnazz","sooniEngName":"Baegna","birthday":"1991-06-01","tall":"157","updateDate":"2025-10-30 06:48:32","soopId":"goodb99","company":"수니뮤직","manager":"","remark":null,"broadCast":"2019-06-19","activeFlag":"Y","sooniName":"배그나","blood":"O","team":"엔소울","sooniCompany":"수니그룹","soopName":"배그나","grade2":"골드3","status":"Y","namu":"배그나","sex":"W","ballon":"386000","position":"팀장","mbti":["ISFP"],"createDate":"2024-10-31 12:26:26","nickHistory":null,"medal":"partner"},{"sooniName":"바비","personName":"","medal":"best","updateDate":"2025-10-30 06:48:32","sex":"W","weight":"45","mbti":null,"namu":null,"company":"수니뮤직","instargram":"@geemamdero.o","soopName":"바비","grade2":"실버5","youtube":"@dog_babi_3","sooniCompany":"수니그룹","activeFlag":"Y","broadCast":"2023-05-08","birthday":"1995-01-21","tall":"162","soopId":"geeworld333","status":"Y","ballon":"167772","createDate":"2025-03-14 15:52:54","remark":null,"position":"","sooniEngName":null,"nickHistory":"웃찌이,개바비","team":"엔소울","blood":"O","manager":null,"grade":"실버"},{"youtube":"@An_Yeseul_Ddi","instargram":"indy1028","broadCast":"2021-03-07","soopId":"indy1028","soopName":"안예슬띠","activeFlag":"Y","medal":"partner","weight":"48","tall":"161","blood":"O","sex":"W","grade2":"실버3","sooniName":"안예슬","sooniEngName":"AnYeSeul","mbti":["INTJ"],"personName":"안예슬","nickHistory":null,"namu":"안예슬","company":"수니뮤직","ballon":"207000","updateDate":"2025-10-30 06:48:32","remark":"슈퍼스타K4, 프로듀스 101","manager":"","activaFlag":null,"status":"Y","grade":"실버","birthday":"1995-10-28","sooniCompany":"수니그룹","createDate":"2024-10-31 12:26:26","team":"엔소울","position":""},{"sooniCompany":"수니그룹","soopName":"욘서","broadCast":"2025-05-06","grade":"실버","company":"수니뮤직","medal":"basic","grade2":"브론즈1","sex":"W","mbti":["INFP"],"personName":"권연서","activeFlag":"Y","soopId":"qmffnqurwl","weight":"46","ballon":"162124","tall":"162","status":"Y","instargram":"yyss_030","updateDate":"2025-10-30 06:48:32","nickHistory":null,"remark":null,"createDate":"2025-05-06 23:48:25","blood":"A","position":"","manager":"","sooniEngName":"","youtube":null,"namu":null,"sooniName":"욘서","team":"엔소울","birthday":"1997-12-10"},{"grade2":"브론즈3","medal":"best","soopId":"dockyong","birthday":"1985-08-02","sooniName":"덕이형","mbti":["ISTP"],"blood":"B","weight":null,"company":"수니뮤직","status":"Y","updateDate":"2025-10-30 06:48:32","manager":null,"grade":"브론즈","namu":"덕이튜브","position":"","youtube":"channel/UCjkevnaCbANXTNMt1vjJowQ","createDate":"2024-11-22 16:02:43","nickHistory":null,"personName":"김용덕","sooniCompany":"수니그룹","broadCast":"2018-02-18","activeFlag":"Y","team":"엔소울","soopName":"덕이형","sooniEngName":null,"remark":null,"sex":"M","ballon":"68111","instargram":"ok_deok","tall":"177"},{"tall":"167","sooniCompany":"수니그룹","soopId":"gptn1109","grade2":"실버6","updateDate":"2025-10-30 06:48:32","sooniName":"킴아연","broadCast":"2025-09-15","manager":"","team":"수니힐","grade":"실버","activeFlag":"Y","sooniEngName":"Ayeon97","status":"Y","remark":null,"youtube":"@ayeon97","namu":"킴아연","birthday":"1997-11-09","position":"팀장","weight":"52","blood":"B","ballon":"166919","soopName":"킴아연","personName":"전혜수","createDate":"2025-09-20 23:20:33","mbti":["ISTP","INFP"],"instargram":"zn_ayeon97","company":"수니뮤직","medal":"basic","sex":"W","nickHistory":null},{"grade2":"브론즈1","soopName":"뮤링","instargram":null,"grade":"브론즈","activeFlag":"Y","medal":"best","team":"수니힐","birthday":"2000-11-13","tall":"161","sooniName":"뮤링","broadCast":"2024-11-19","weight":"45","namu":null,"mbti":["ENTJ"],"updateDate":"2025-10-30 06:48:32","createDate":"2025-01-22 10:48:24","remark":null,"sooniEngName":"MuRing","position":"","sooniCompany":"수니그룹","nickHistory":null,"blood":"AB","manager":null,"personName":"박수민","sex":"W","status":"Y","soopId":"dmswjd326","company":"수니뮤직","ballon":"125388","youtube":null},{"activeFlag":"Y","createDate":"2025-09-18 00:25:25","sooniEngName":null,"status":"Y","ballon":"20015","sooniCompany":"수니그룹","position":"","nickHistory":null,"soopName":"영베리","soopId":"gkksdk7777","manager":"","namu":null,"team":"수니힐","grade2":"브론즈8","grade":"브론즈","medal":"basic","sex":"W","remark":null,"instargram":null,"mbti":["INTJ"],"broadCast":"2025-09-08","birthday":"2003","weight":null,"personName":null,"blood":null,"company":"수니뮤직","sooniName":"영베리","updateDate":"2025-10-30 06:48:32","tall":"160","youtube":null},{"grade2":"브론즈6","manager":"","soopName":"도욤","updateDate":"2025-10-30 06:48:32","status":"Y","soopId":"kwwwo0oa","instargram":null,"sooniName":"도욤","sooniEngName":"","grade":"브론즈","blood":null,"team":"수니힐","activeFlag":"Y","tall":"160","sooniCompany":"수니그룹","broadCast":"2025-08-13","position":"","ballon":"35500","medal":"basic","namu":null,"personName":"?다정","remark":null,"youtube":null,"nickHistory":null,"company":"수니뮤직","createDate":"2025-08-14 10:34:37","mbti":null,"birthday":"1995","weight":"44","sex":"W"},{"remark":null,"grade":"브론즈","soopName":"쑤","ballon":"60307","manager":"","youtube":null,"soopId":"sisterssu","position":"","createDate":"2025-07-01 10:43:05","namu":null,"status":"Y","team":"수니힐","sooniEngName":"SSU","personName":"","company":"수니뮤직","birthday":"1999-08-09","sooniName":"쑤","sex":"W","nickHistory":null,"medal":"best","weight":"48","mbti":["ISFP"],"updateDate":"2025-11-01 20:12:49","sooniCompany":"수니그룹","broadCast":"2025-07-01","grade2":"브론즈4","tall":"166","blood":"A","instargram":"sister_ssu","activeFlag":"Y"},{"createDate":"2025-10-31 23:49:25","status":"Y","youtube":null,"updateDate":"2025-11-01 20:31:00","activeFlag":"Y","nickHistory":null,"namu":"빈하늘","blood":"O","grade2":"언랭","personName":"빈하늘","position":"인턴","birthday":"1999-12-14","instargram":"haneul_bin","sooniCompany":"수니그룹","ballon":"","soopId":"bean1214","remark":null,"manager":"","soopName":"♡비니♡","sex":"W","company":"수니뮤직","medal":"basic","weight":null,"sooniEngName":null,"team":"수니힐","broadCast":null,"grade":"언랭","sooniName":"비니","mbti":null,"tall":"168"},{"mbti":["ENTP"],"sooniCompany":"수니그룹","sex":"W","namu":"조이온","tall":"158","blood":"A","broadCast":"2024-12-08","manager":"","birthday":"2000-08-01","remark":null,"company":"수니뮤직","sooniEngName":"Joy_.on","grade2":"언랭","updateDate":"2025-11-01 20:31:00","grade":"언랭","activeFlag":"Y","nickHistory":null,"team":"수니힐","sooniName":"조이온","instargram":"joy_.on","status":"Y","weight":"48","youtube":"@Joy_on","soopId":"juju0081","soopName":"조이온","position":"인턴","personName":"조유주","ballon":null,"medal":"best","createDate":"2025-01-22 10:48:24"},{"position":"팀장","blood":"O","sooniName":"서우연","activeFlag":"Y","tall":null,"soopId":"savuswl","nickHistory":null,"sex":"M","updateDate":"2025-10-30 06:48:51","youtube":null,"status":"Y","company":"수니뮤직","personName":"서인수","soopName":"서우연","mbti":["ISFP"],"medal":"best","team":"엔뮤즈","weight":null,"birthday":"1991-08-31","createDate":"2025-06-26 21:55:50","sooniEngName":null,"remark":null,"sooniCompany":"수니그룹","manager":"","grade2":"브론즈9","grade":"브론즈","ballon":"13567","instargram":null,"namu":null,"broadCast":null},{"sooniCompany":"수니그룹","activeFlag":"Y","soopName":"채수아","status":"Y","mbti":["ESTP"],"nickHistory":null,"grade2":"골드2","sooniEngName":"","updateDate":"2025-10-30 06:50:04","team":"블랙","broadCast":"2025-07-15","tall":"160","birthday":"1991-10-24","manager":"사장","youtube":null,"position":"","grade":"골드","blood":"A","ballon":"471637","soopId":"youyou0708","instargram":"sy._.10.24","sex":"W","medal":"basic","namu":null,"personName":"김시연","weight":"51","sooniName":"채수아","createDate":"2025-07-16 22:46:47","remark":null,"company":"수니엔터"},{"instargram":"minseoyool","personName":"김예지","soopId":"b24ip7","soopName":"민서율","status":"Y","birthday":"1996-06-04","sex":"W","remark":null,"youtube":"@minseoyool","sooniName":"민서율","mbti":"ENTP","updateDate":"2025-10-30 06:50:04","createDate":"2024-10-31 12:26:26","medal":"best","tall":"162","position":"팀장","nickHistory":null,"ballon":"541888","company":"수니엔터","grade2":"플래티넘","weight":"47","sooniCompany":"수니그룹","team":"블랙","grade":"플래티넘","activeFlag":"Y","manager":"부회장","namu":"민서율","sooniEngName":"MinSeoYul","blood":"A","broadCast":"2021-01-13"},{"soopId":"dbwls991","company":"수니엔터","birthday":"1996-09-14","soopName":"유진냥","position":"","createDate":"2025-05-29 21:19:11","manager":"","sex":"W","weight":"49","status":"Y","remark":null,"updateDate":"2025-10-30 06:50:04","namu":"유진냥","instargram":"yujin__o_o","broadCast":"2024-03-11","activeFlag":"Y","grade":"골드","tall":"168","team":"블랙","medal":"best","grade2":"골드4","nickHistory":null,"blood":"A","youtube":"@yujinnyang","sooniCompany":"수니그룹","personName":"임유진","sooniEngName":"YuJinNyang","sooniName":"유진냥","mbti":["ESTP"],"ballon":"358409"},{"medal":"best","namu":null,"soopName":"설유은","personName":"변서희","tall":"160","grade":"실버","createDate":"2025-02-15 00:28:15","mbti":["ENFP"],"soopId":"byunseo456","birthday":"2000-05-29","grade2":"실버2","team":"블랙","nickHistory":null,"sooniCompany":"수니그룹","activeFlag":"Y","remark":null,"blood":"B","youtube":"@ueuni._.00","ballon":"207282","broadCast":"2025-02-14","updateDate":"2025-10-30 06:50:04","instargram":"ueuni._.00","position":"","sooniName":"설유은","sooniEngName":null,"company":"수니엔터","sex":"W","status":"Y","manager":"","weight":"46"},{"mbti":["ENTJ"],"weight":"52","remark":null,"team":"블랙","tall":"168","manager":null,"birthday":"2002-02-09","sex":"W","grade":"실버","grade2":"실버4","activeFlag":"Y","broadCast":"2025-01-22","updateDate":"2025-10-30 06:50:04","status":"Y","namu":null,"soopId":"yuzzzz","sooniName":"유즈","position":"","medal":"best","sooniEngName":"Yuze","youtube":null,"personName":"정유진","sooniCompany":"수니그룹","nickHistory":null,"ballon":"174984","createDate":"2025-01-22 10:48:24","instargram":"_yuze__","soopName":"유즈","blood":"A","company":"수니엔터"},{"tall":"162","instargram":"@zyunni_","createDate":"2025-04-02 23:59:13","position":"","birthday":"2001-06-05","mbti":["ISTP"],"soopId":"zyunnyang","blood":"A","sooniCompany":"수니그룹","grade2":"실버1","company":"수니엔터","manager":"","sooniEngName":"Junie","activeFlag":"Y","status":"Y","sooniName":"쥬니","remark":null,"sex":"W","updateDate":"2025-10-30 06:50:04","youtube":"@zyunnyang","medal":"best","nickHistory":null,"grade":"실버","soopName":"쥬니","ballon":"333604","weight":"51","personName":"권지윤","team":"블랙","broadCast":"2025-04-02","namu":null},{"remark":null,"grade":"실버","position":"팀장","medal":"best","ballon":"166070","team":"화이트","nickHistory":null,"soopName":"수빙","activeFlag":"Y","personName":"진이수","createDate":"2025-04-02 23:53:12","weight":"48","sooniName":"수빙","instargram":"puppylllllove","soopId":"flwjdtls","sooniEngName":"SuBing","company":"수니엔터","broadCast":"2023-03-28","sooniCompany":"수니그룹","manager":null,"birthday":"2001-06-27","namu":null,"grade2":"실버7","sex":"W","tall":"161","status":"Y","mbti":["ENFP"],"youtube":"@subing01","blood":"A","updateDate":"2025-10-30 06:50:04"},{"broadCast":"2025-07-10","createDate":"2025-07-11 00:11:35","grade2":"브론즈5","birthday":"1998","manager":"","sex":"W","sooniCompany":"수니그룹","medal":"basic","remark":"","nickHistory":null,"soopId":"s0ngaji123","position":"","mbti":["ISFP"],"company":"수니엔터","status":"Y","sooniName":"송지안","instargram":"with_dia","activeFlag":"Y","namu":null,"youtube":null,"ballon":"47789","weight":"55","soopName":"송지안","team":"화이트","personName":"","blood":"O","tall":"168","sooniEngName":"","updateDate":"2025-10-30 06:50:04","grade":"브론즈"},{"company":"수니엔터","broadCast":"2015-01-15","mbti":["INFP"],"remark":null,"sex":"W","manager":"","personName":"한은비","updateDate":"2025-11-01 20:31:00","createDate":"2025-11-01 20:11:57","soopName":"벨비","ballon":null,"activeFlag":"Y","tall":"165","youtube":null,"sooniEngName":"","team":"화이트","blood":"O","instargram":"eunbi._.han","grade2":"언랭","sooniName":"벨비","nickHistory":null,"grade":"언랭","position":"인턴","weight":"52","medal":"best","soopId":"hanb1128","birthday":"1992-11-28","status":"Y","sooniCompany":"수니그룹","namu":"벨비"},{"team":"그레이","namu":null,"mbti":["ESTJ","ENTJ"],"sooniName":"김태룡","medal":"best","createDate":"2025-04-24 23:22:12","sooniCompany":"수니그룹","position":"팀장","grade":"브론즈","remark":null,"youtube":null,"soopId":"rlaxofyd96","grade2":"브론즈7","soopName":"김태룡","personName":null,"sex":"M","blood":"O","status":"Y","nickHistory":null,"instargram":null,"tall":"180","birthday":"1996-12-17","manager":"","sooniEngName":null,"broadCast":"2023-06-01","company":"수니엔터","activeFlag":"Y","weight":null,"updateDate":"2025-10-30 06:50:04","ballon":"24220"},{"team":"","sooniName":"펭채은","activeFlag":"Y","blood":"AB","soopName":"펭채은","soopId":"qorhvk1365","youtube":"@펭채은","sex":"W","namu":null,"medal":"best","personName":"강혜인","grade2":"","birthday":"1999-09-29","mbti":["ISFJ"],"manager":"","broadCast":"2024-07-06","sooniCompany":"수니그룹","instargram":"aisaka_taiga_____","sooniEngName":"ChaeEun","remark":null,"position":"휴직","tall":"160","updateDate":"2025-10-25 23:11:20","status":"Y","company":"","nickHistory":null,"createDate":"2024-10-31 12:26:26","weight":"52","ballon":"170871","grade":"브론즈"},{"grade":"브론즈","sex":"W","grade2":"","birthday":"2004-05-06","sooniCompany":"수니그룹","sooniName":"남민아","position":"휴직","remark":null,"namu":null,"soopName":"남민아","team":"","blood":"B","tall":"155","broadCast":"2025-08-23","manager":"","activeFlag":"Y","sooniEngName":"MinA","status":"Y","youtube":"@NamminaReacts","personName":"남경민","createDate":"2025-08-23 21:46:53","company":"","nickHistory":null,"medal":"basic","weight":null,"ballon":"82486","soopId":"zzam2da","instargram":"owallsix","mbti":["ENTJ"],"updateDate":"2025-10-25 23:10:54"},{"sooniEngName":"Sangyoon","soopName":"나는상윤","remark":"수니게임즈 사장, 한전드","team":null,"company":null,"broadCast":null,"position":null,"medal":"partner","createDate":"2024-10-31 12:26:26","manager":"사장","grade":null,"mbti":"ESTP","activeFlag":"Y","sooniName":"나는상윤","tall":"174","blood":null,"status":"Y","instargram":"kwonsy95","weight":null,"youtube":"@나는상윤","sooniCompany":"수니게임즈","soopId":"sky2713","nickHistory":null,"birthday":"1995-12-20","personName":"권상윤","sex":"M","namu":"권상윤","updateDate":"2025-07-18 10:40:39"},{"updateDate":"2025-06-15 20:40:02","blood":"O","birthday":"1996-08-21","tall":"159","weight":null,"soopId":"hyn8210","youtube":"@rabbityena","sex":"W","sooniName":"토끼예나","status":"Y","createDate":"2025-01-01 17:59:43","sooniEngName":null,"mbti":["INTP","INFP"],"activeFlag":"Y","broadCast":"2017-05-14","soopName":"토끼예나","instargram":"rabbit_yena_","namu":"토끼예나","sooniCompany":"수니게임즈","remark":null,"medal":"best","personName":"허예나"},{"status":"Y","activaFlag":null,"nickHistory":null,"updateDate":"2025-07-22 21:53:52","weight":null,"broadCast":"2023-07-22","instargram":null,"soopName":"헤니","tall":null,"medal":"best","youtube":null,"mbti":["ISFP"],"sooniEngName":null,"namu":null,"activeFlag":"Y","team":null,"remark":"수니게임즈 멤버","createDate":"2024-10-31 12:26:26","soopId":"jhw215","position":null,"blood":"B","grade":null,"sooniCompany":"수니게임즈","sex":"W","company":null,"birthday":"1997-02-15","manager":null,"sooniName":"헤니","personName":null},{"tall":"168","updateDate":"2025-10-04 12:38:54","namu":"박나닝","sooniCompany":"수니게임즈","position":"","status":"Y","sooniName":"박나닝","sooniEngName":null,"broadCast":"2018-05-08","mbti":null,"personName":"박나은","birthday":"1993-08-02","soopName":"박나닝","activeFlag":"Y","youtube":"@park_naning","sex":"W","manager":"","instargram":null,"nickHistory":null,"weight":null,"medal":"best","team":"","grade":"","remark":null,"blood":null,"soopId":"na2un","company":"","createDate":"2025-10-04 12:38:54"},{"namu":null,"instargram":null,"grade":"","sooniCompany":"수니게임즈","team":"","sex":"W","broadCast":"2022-10-04","company":"","soopId":"tleod1818","createDate":"2025-08-03 21:10:15","position":"","sooniName":"빙밍","sooniEngName":"Vingming","tall":"152","updateDate":"2025-08-07 22:47:57","soopName":"빙밍","manager":"","personName":null,"weight":null,"blood":"O","status":"Y","birthday":"2001-07-07","activeFlag":"Y","medal":"best","nickHistory":null,"youtube":"@qldald_2","remark":"첫 버튜버 영입","mbti":["ENFP"]},{"status":"Y","instargram":"282bb","sooniName":"별비","manager":null,"blood":"B","youtube":null,"soopName":"별비^00^","medal":"best","mbti":["INFJ"],"birthday":"1991-06-24","grade":null,"broadCast":"2016-11-25","team":null,"soopId":"xvvx1859","createDate":"2025-01-28 17:32:09","personName":"박별비","sooniEngName":null,"company":null,"weight":"53","sex":"W","sooniCompany":"수니게임즈","remark":null,"activeFlag":"Y","position":"","updateDate":"2025-06-15 20:40:02","namu":"별비(인터넷 방송인)","tall":"167"},{"medal":"best","createDate":"2024-10-31 12:26:26","birthday":"1997-11-20","namu":null,"sooniEngName":"Nyangseul","mbti":["INFP"],"remark":"수니게임즈 멤버","tall":"160","sooniCompany":"수니게임즈","activaFlag":null,"instargram":"daram_seul","soopName":"냥슬","updateDate":"2025-06-15 20:40:02","blood":"A","activeFlag":"Y","weight":null,"personName":"김예슬","soopId":"yeseul1120","sooniName":"냥슬","broadCast":"2019-01-04","youtube":"yeseuli1120","status":"Y","sex":"W"},{"weight":null,"broadCast":null,"soopId":"youjamjam","status":"Y","soopName":"유잼이","position":"","namu":null,"sooniName":"유잼이","youtube":"@youjamjam","instargram":"youjam_jam","remark":null,"birthday":"1997-06-10","sooniCompany":"수니게임즈","nickHistory":null,"blood":"A","sooniEngName":"","medal":"best","team":"","manager":"","personName":"","createDate":"2025-05-05 23:03:20","tall":"162","company":"","sex":"W","updateDate":"2025-07-31 21:23:42","grade":"","mbti":["ISTP"],"activeFlag":"Y"},{"tall":"147","sooniCompany":"수니문","soopId":"bibitrue","updateDate":"2025-10-11 22:28:52","sooniName":"비쥬","broadCast":"2022-01-11","team":"","manager":"사장","grade":"","activeFlag":"Y","sooniEngName":"Bijou","status":"Y","remark":"수니버츄얼? 인턴","youtube":"@비쥬_Bijou","namu":"비쥬(인터넷 방송인)","birthday":"1999-04-20","position":"","weight":null,"blood":null,"soopName":"비쥬","personName":"","createDate":"2025-09-06 20:11:03","mbti":null,"instargram":"","medal":"best","company":"","sex":"W","nickHistory":null},{"remark":null,"company":null,"weight":"","soopName":"시로코","grade":null,"manager":null,"soopId":"k0roshi","sooniCompany":"수니문","sooniEngName":"Shiroko","medal":"best","broadCast":"2022-10-05","youtube":"@shiroko_o3o","sex":"W","mbti":["ISTJ"],"personName":"이나다 유미","activeFlag":"Y","namu":"시로코(인터넷 방송인)","sooniName":"시로코","createDate":"2025-09-13 22:16:49","birthday":"2001-10-02","blood":"B","updateDate":"2025-10-11 22:29:10","nickHistory":null,"tall":"161","status":"Y","team":null,"instargram":"shiroko_o3o","position":null},{"soopName":"콧시","broadCast":null,"personName":null,"activeFlag":"Y","remark":null,"youtube":"@cozy_sea","soopId":"oss0930","sooniCompany":"수니문","company":null,"weight":null,"grade":null,"updateDate":"2025-10-11 22:29:10","medal":"best","team":null,"status":"Y","position":null,"sooniEngName":"Cozysea","nickHistory":null,"sooniName":"콧시","namu":null,"sex":"M","createDate":"2025-09-13 22:16:49","mbti":["ISFJ"],"blood":null,"manager":null,"tall":"180","instargram":"co_zys_ea","birthday":"1998-09-30"},{"weight":null,"team":null,"createDate":"2025-09-13 22:16:49","birthday":"2004-02-07","broadCast":"2022-10-16","youtube":"@Lin9hana_27","medal":"best","blood":null,"updateDate":"2025-10-11 22:29:10","position":null,"manager":"","company":null,"grade":null,"activeFlag":"Y","sooniName":"하나링구","mbti":["ISFP"],"sooniEngName":"Lin9hana","sex":"W","soopName":"하나링구","tall":"167","status":"Y","sooniCompany":"수니문","soopId":"skfk6612","instargram":"","remark":null,"personName":null,"nickHistory":null,"namu":"하나링구"},{"nickHistory":null,"instargram":null,"medal":"best","namu":"서피카","company":null,"activeFlag":"Y","sex":"W","team":null,"sooniCompany":"수니문","mbti":["ENFP"],"soopName":"서피카","grade":null,"createDate":"2025-09-13 22:16:49","sooniName":"서피카","status":"Y","weight":null,"broadCast":"2022-10-28","remark":null,"youtube":"@SEOPICA","sooniEngName":"SEOPICA","personName":null,"blood":null,"birthday":"????-02-21","tall":"164","position":null,"updateDate":"2025-10-11 22:29:10","soopId":"spica21","manager":null},{"sooniEngName":"Tinkerblond","sooniCompany":"수니문","createDate":"2025-09-13 22:16:49","namu":"더빙레이디","team":null,"soopId":"tinkerblond","remark":null,"manager":null,"updateDate":"2025-10-11 22:29:10","youtube":"@dubbinglady","sooniName":"더빙레이디","personName":"김태희","grade":null,"broadCast":"","company":null,"status":"Y","birthday":"1994-11-16","mbti":[],"nickHistory":null,"soopName":"더빙레이디","sex":"W","instargram":"dubbinglady","weight":"","activeFlag":"Y","position":null,"tall":"164","medal":"best","blood":"O"}]